[
	/* Ancient Era */
	{
		"name": "Worker Drone",
		"unitType": "Civilian",
		"movement": 2,
		"hurryCostModifier": 20,
		"uniques": ["Can build improvements on tiles"],
		"cost": 70
	},
	{
		"name": "Spawning Drone",
		"unitType": "Civilian",
		"movement": 2,
		"cost": 105,
		"uniques": ["Founds a new city","Requires at least [2] population","Excess Food converted to Production when under construction"],
		"hurryCostModifier": 20
	},
	{
		"name": "Synapse Drone",
		"unitType": "Civilian",
		"uniques": ["Can start an [8]-turn golden age","Cannot be purchased"],
		"cost": 280,
		"hurryCostModifier": 20,
		"requiredTech": "Introspection",
		"movement": 1
	},
	{
		"name": "Storage Drone",
		"unitType": "Civilian",
		"uniques": ["Can speed up construction of a wonder","Cannot be purchased"],
		"cost": 150,
		"hurryCostModifier": 20,
		"requiredTech": "Stockpiling Instincts",
		"movement": 1
	},
	{
		"name": "Mnemonic Drone",
		"unitType": "Civilian",
		"uniques": ["Can hurry technology research","Cannot be purchased"],
		"cost": 250,
		"hurryCostModifier": 20,
		"requiredTech": "Stockpiling Instincts",
		"movement": 1
	},
	{
		"name": "Scouting Drone",
		"unitType": "Scout",
		"movement": 2,
		"strength": 5,
		"cost": 25,
		"uniques": ["Ignores terrain cost"],
		"attackSound": "nonmetalhit"
	},
	{
		"name": "Soldier Drone",
		"unitType": "Melee",
		"movement": 2,
		"strength": 8,
		"cost": 40,
		"hurryCostModifier": 20,
		"obsoleteTech": "Bio-Weapons",
		"upgradesTo": "Slasher",
		"attackSound": "nonmetalhit"
	},
	{
		"name": "Slasher",
		"unitType": "Melee",
		"movement": 2,
		"strength": 12,
		"cost": 40,
		"hurryCostModifier": 20,
		"requiredTech": "Bio-Weapons",
		"obsoleteTech": "Symbiotic Weaponry",
		"upgradesTo": "Slasher Symbiont",
		"attackSound": "nonmetalhit"
	},
	{
		"name": "Spitter",
		"unitType": "Ranged",
		"movement": 2,
		"strength": 5,
		"rangedStrength": 7,
		"cost": 40,
		"hurryCostModifier": 20,
		"requiredTech": "Bio-Weapons",
		"obsoleteTech": "Symbiotic Weaponry",
		"upgradesTo": "Spitter Symbiont",
		"attackSound": "arrow"
	},
	{
		"name": "Aquatic Drone",
		"unitType": "WaterCivilian",
		"movement": 4,
		"cost": 30,
		"requiredTech": "Aquatic Adaptations",
		"uniques": ["Cannot enter ocean tiles until Astronomy", "May create improvements on water resources"],
		"hurryCostModifier": 20
	},
	{
		"name": "Carrier Drone",
		"unitType": "WaterMelee",
		"movement": 4,
		"strength": 10,
		"cost": 45,
		"requiredTech": "Aquatic Adaptations",
		"uniques": ["Cannot enter ocean tiles"],
		//"upgradesTo": "Caravel",
		//"obsoleteTech": "Astronomy",
		"hurryCostModifier": 20,
		"attackSound": "nonmetalhit"
	},
	{
		"name": "Warbeast",
		"unitType": "Mounted",
		"movement": 3,
		"strength": 18,
		"cost": 75,
		"requiredTech": "Gene Harvesting",
		"requiredResource": "Wildlife",
		//"upgradesTo": "Knight",
		//"obsoleteTech": "Chivalry",
		"uniques": ["No defensive terrain bonus","Bonus vs Melee 33%"],
		"hurryCostModifier": 20,
		"attackSound": "horse"
	},
	{
		"name": "Gene Cyst",
		"unitType": "Missile",
		"movement": 1,
		"strength": 30,
		"rangedStrength": 30,
		"range": 3,
		"cost": 30,
		"requiredTech": "Gene Harvesting",
		//"requiredResource": "Wildlife",
		"uniques": ["Excess Food converted to Production when under construction"]
	},
	{
		"name": "Gunbeast",
		"unitType": "Ranged",
		"movement": 3,
		"strength": 10,
		"rangedStrength": 14,
		"cost": 75,
		"requiredTech": "Gene Weaponry",
		"requiredResource": "Wildlife",
		//"upgradesTo": "Knight",
		//"obsoleteTech": "Chivalry",
		"uniques": ["No defensive terrain bonus","Bonus vs Melee 33%"],
		"hurryCostModifier": 20,
		"attackSound": "arrow"
	},
	{
		"name": "Bio-titan",
		"unitType": "Siege",
		"movement": 2,
		"strength": 25,
		"rangedStrength": 30,
		"cost": 175,
		"requiredTech": "Titanic Weaponry",
		//"requiredResource": "Wildlife",
		//"upgradesTo": "Knight",
		//"obsoleteTech": "Chivalry",
		"uniques": ["No defensive terrain bonus","Bonus vs City 200%","Penalty vs Ranged 33%"],
		"hurryCostModifier": 20,
		"attackSound": "arrow"
	},
	{
		"name": "Telekinetic Drone",
		"unitType": "Ranged",
		"movement": 2,
		"range": 5,
		"strength": 3,
		"rangedStrength": 7,
		"cost": 50,
		"hurryCostModifier": 20,
		"requiredTech": "Chronostasis",
		//"obsoleteTech": "Machinery",
		//"upgradesTo": "Crossbowman",
		"uniques": ["Ignores terrain cost", "+[100]% Strength vs [Armor]", "6 tiles in every direction always visible", "Ranged attacks may be performed over obstacles"],
		"attackSound": "arrow"
	},
	{
		"name": "Impaler",
		"unitType": "Melee",
		"movement": 2,
		"strength": 14,
		"cost": 50,
		"requiredTech": "Mineral Adaptations",
		//"obsoleteTech": "Civil Service",
		//"upgradesTo": "Pikeman",
		"uniques": ["Bonus vs Mounted 100%","Penalty vs Melee 50%"],
		"hurryCostModifier": 20,
		"attackSound": "metalhit"
	},
	{
		"name": "Armor Drone",
		"unitType": "Armor",
		"movement": 1,
		"strength": 15,
		"cost": 75,
		"requiredTech": "Mineral Adaptations",
		//"obsoleteTech": "Civil Service",
		//"upgradesTo": "Pikeman",
		"uniques": ["Bonus vs Ranged 100%", "+[100]% Strength when defending"]
		"hurryCostModifier": 20,
		"attackSound": "horse"
	},
	{
		"name": "Spitter Symbiont",
		"unitType": "Ranged",
		"movement": 2,
		"strength": 5,
		"rangedStrength": 12,
		"cost": 50,
		"hurryCostModifier": 20,
		"requiredTech": "Symbiotic Weaponry",
		//"obsoleteTech": "Machinery",
		//"upgradesTo": "Crossbowman",
		"attackSound": "arrow"
	},
	{
		"name": "Slasher Symbiont",
		"unitType": "Melee",
		"movement": 2,
		"strength": 16,
		"cost": 50,
		"hurryCostModifier": 20,
		"requiredTech": "Symbiotic Weaponry",
		//"obsoleteTech": "Machinery",
		//"upgradesTo": "Crossbowman",
		"attackSound": "nonmetalhit"
	},
	/* Archaic Era */
	{
		"name": "Shredder",
		"unitType": "Melee",
		"movement": 3,
		"strength": 14,
		"cost": 60,
		"requiredTech": "Adaptive Weaponry",
		//"obsoleteTech": "Civil Service",
		//"upgradesTo": "Pikeman",
		"uniques":["Bonus as Attacker [100]%", "Bonus vs Armor 100%"],
		"hurryCostModifier": 20,
		"attackSound": "metalhit"
	},
	
	// Unbuildables
	{
		"name": "Great Psyker",
		"unitType": "Civilian",
		"uniques": ["Can start an [16]-turn golden age", "Can construct [Mind Nexus]", "Great Person - [Culture]", "Unbuildable"],
		"movement": 2
	},
	{
		"name": "Great Catalyst",
		"unitType": "Civilian",
		"uniques": ["Can hurry technology research", "Can construct [Science Nexus]", "Great Person - [Science]", "Unbuildable"],
		"movement": 2
	},
	{
		"name": "Great Scion",
		"unitType": "Civilian",
		"uniques": ["Can undertake a trade mission with City-State, giving a large sum of gold and [100] Influence","Can construct [Material Nexus]", "Great Person - [Gold]", "Unbuildable"],
		"movement": 2
	},
	{
		"name": "Great Overseer",
		"unitType": "Civilian",
		"uniques": ["Can speed up construction of a wonder", "Can construct [Production Nexus]", "Great Person - [Production]", "Unbuildable"],
		"movement": 2
	},
	{
		"name": "Great Warrior",
		"unitType": "Civilian",
		"uniques": ["Can start an [8]-turn golden age", "Bonus for units in 2 tile radius 15%", "Can construct [Defensive Nexus]",
			"Great Person - [War]", "Unbuildable"],
		"movement": 2
	},
	// Nation Uniques
	{
		"name": "Rak'tar Swarm Drone",
		"uniqueTo": "Rak'tar",
		"replaces": "Soldier Drone",
		"unitType": "Melee",
		"movement": 2,
		"strength": 9,
		"cost": 10,
		"hurryCostModifier": 20,
		"promotions": ["Call of the Swarm"],
		"obsoleteTech": "Bio-Weapons",
		"upgradesTo": "Slasher",
		"attackSound": "nonmetalhit"
	},
	{
		"name": "Kezit Catalyst Drone",
		"uniqueTo": "Kezit",
		"replaces": "Synapse Drone",
		"unitType": "Civilian",
		"uniques": ["Can start an [8]-turn golden age","Can hurry technology research","Cannot be purchased"],
		"cost": 240,
		"hurryCostModifier": 20,
		"requiredTech": "Introspection",
		"movement": 1
	},
	{
		"name": "Int'uu Queen",
		"unitType": "Civilian",
		"uniques": ["Can start an [50]-turn golden age", "Can construct [Mind Nexus]", "Can construct [Pheromone Nexus]", "Great Person - [Culture]", "Unbuildable"],
		"movement": 2,
		"uniqueTo": "Int'uu",
		"replaces": "Great Psyker"
	},
	{
		"name": "Tsan'tai Seeker Drone",
		"unitType": "Scout",
		"uniques": ["Ignores terrain cost", "Can undertake a trade mission with City-State, giving a large sum of gold and [35] Influence","Cannot be purchased"],
		"movement": 5,
		"strength": 2,
		"cost": 25,
		"uniqueTo": "Tsan'tai",
		"replaces": "Scouting Drone"
	},
	
	//City-State Uniques
	{
		"name": "Sekari Shellwalker",
		"uniqueTo": "Sekari",
		"replaces": "Soldier Drone",
		"unitType": "Melee",
		"movement": 1,
		"strength": 10,
		"cost": 40,
		"hurryCostModifier": 20,
		//"requiredTech": "",
		//"requiredResource": "",
		"upgradesTo": "Slasher",
		"obsoleteTech": "Bio-Weapons",
		"uniques": ["+25% Defence against ranged attacks"],
		"promotions": ["Reflective Carapace"],
		"attackSound": "horse"
	},
	{
		"name": "Katorian Tunneler",
		"uniqueTo": "Kator",
		"replaces": "Warbeast",
		"unitType": "Mounted",
		"movement": 4,
		"strength": 21,
		"cost": 75,
		"hurryCostModifier": 20,
		//"requiredTech": "",
		//"requiredResource": "",
		//"upgradesTo": "",
		//"obsoleteTech": "",
		"uniques": ["Invisible to others"],
		"promotions": ["Bio-Static Spines"],
		"attackSound": "horse"
	},
	{
		"name": "Venixian Mind-Eater",
		"uniqueTo": "Venix",
		"replaces": "Impaler",
		"unitType": "Melee",
		"movement": 2,
		"strength": 16,
		"cost": 50,
		"requiredTech": "Mineral Adaptations",
		//"requiredTech": "",
		//"requiredResource": "",
		//"upgradesTo": "",
		//"obsoleteTech": "",
		"uniques": ["Bonus vs Mounted 25%","Bonus vs Melee 25%","Can move after attacking"],
		"promotions": ["Feeding Tendrils"],
		"hurryCostModifier": 20,
		"attackSound": "metalhit"
	},
	{
		"name": "Zyxian Shrieker",
		"uniqueTo": "Zyxia",
		"replaces": "Spitter",
		"unitType": "Ranged",
		"movement": 2,
		"strength": 1,
		"range": 1,
		"rangedStrength": 12,
		"cost": 40,
		"hurryCostModifier": 20,
		"requiredTech": "Bio-Weapons",
		"uniques": ["+[100]% Strength when attacking"],
		"promotions": ["Supersonic Vibrations"],
		"obsoleteTech": "Symbiotic Weaponry",
		"upgradesTo": "Spitter Symbiont",
		"attackSound": "arrow"
	},
	//Wildlife
	/*
	{
		"name": "Great Devourer",
		"unitType": "Siege",
		"uniqueTo": "Barbarians",
		"replaces": "Bio-Titan",
		"movement": 1,
		"strength": 50,
		"cost": 200,
		//"obsoleteTech": "Metal Casting",
		//"upgradesTo": "Swordsman",
		"uniques": ["No defensive terrain bonus","Bonus vs Ranged 100%"],
		"attackSound": "nonmetalhit"
	},
	{
		"name": "Predator",
		"unitType": "Mounted",
		"uniqueTo": "Barbarians",
		"replaces": "Warbeast",
		"movement": 3,
		"strength": 20,
		"cost": 140,
		//"obsoleteTech": "Metal Casting",
		//"upgradesTo": "Swordsman",
		"attackSound": "nonmetalhit"
	},
	*/
	//Barbarian Uniques
	{
		"name": "Rogue Drone",
		"unitType": "Melee",
		"uniqueTo": "Barbarians",
		"replaces": "Soldier Drone",
		"movement": 2,
		"strength": 6,
		"cost": 20,
		//"obsoleteTech": "Metal Casting",
		//"upgradesTo": "Swordsman",
		"attackSound": "nonmetalhit"
	}

]